json_decoder/__init__.py
json_decoder/exceptions.py
json_decoder/classes/__init__.py
json_decoder/classes/jsondecoder.py
json_decoder/tests/__init__.py
json_decoder/tests/test_json_decoder/__init__.py
JsonDecoder-0.0.7.dist-info/LICENSE
JsonDecoder-0.0.7.dist-info/METADATA
JsonDecoder-0.0.7.dist-info/WHEEL
JsonDecoder-0.0.7.dist-info/top_level.txt
JsonDecoder-0.0.7.dist-info/RECORD
